forceful_timer/__init__.py
forceful_timer/app_utils.py
forceful_timer/main.py
forceful_timer/title.txt
forceful_timer/ui_utils.py
forceful_timer/utils.py
forceful_timer-0.1.1.dist-info/LICENSE
forceful_timer-0.1.1.dist-info/METADATA
forceful_timer-0.1.1.dist-info/WHEEL
forceful_timer-0.1.1.dist-info/entry_points.txt
forceful_timer-0.1.1.dist-info/top_level.txt
forceful_timer-0.1.1.dist-info/RECORD
