Metadata-Version: 2.1
Name: forceful-timer
Version: 0.1.1
Summary: Forces shutdown once timer runs out or force quits specified applications if timer is interrupted.
Home-page: https://github.com/PraxTube/forceful-timer
Author: Prax
Project-URL: Bug Reports, https://github.com/PraxTube/forceful-timer/issues
Project-URL: Source, https://github.com/PraxTube/forceful-timer
Keywords: timer,shutdown,forcequit
Classifier: Development Status :: 3 - Alpha
Classifier: License :: OSI Approved :: MIT License
Classifier: Programming Language :: Python :: 3
Classifier: Programming Language :: Python :: 3.8
Classifier: Programming Language :: Python :: 3.9
Classifier: Programming Language :: Python :: 3.10
Classifier: Programming Language :: Python :: 3 :: Only
Requires-Python: >=3.8, <4
License-File: LICENSE
Requires-Dist: chime
Requires-Dist: tqdm
